{
    "5OCWB8IQJU6A": {
        "days": 3,
        "created_at": "2026-04-16T23:44:52.465553",
        "used": true,
        "used_by": 7708627627,
        "used_at": "2026-04-16T23:44:58.719719"
    },
    "YWYEK59NB7RI": {
        "days": 3,
        "created_at": "2026-04-16T23:56:43.008819",
        "used": false,
        "used_by": null
    },
    "6IRHI1NDVMEG": {
        "days": 3,
        "created_at": "2026-04-16T23:56:53.877937",
        "used": false,
        "used_by": null
    },
    "5EGW69N6V9RM": {
        "days": 3,
        "created_at": "2026-04-16T23:56:53.877960",
        "used": false,
        "used_by": null
    },
    "7V4R3SJI4NYO": {
        "days": 3,
        "created_at": "2026-04-16T23:56:53.877966",
        "used": false,
        "used_by": null
    },
    "QZYV496NVZ4Z": {
        "days": 10,
        "created_at": "2026-04-17T00:52:12.610516",
        "used": false,
        "used_by": null
    },
    "YZMWA1F0ARNB": {
        "days": 10,
        "created_at": "2026-04-17T00:52:23.246966",
        "used": false,
        "used_by": null
    },
    "YVBCLZ3OFAQX": {
        "days": 1,
        "created_at": "2026-04-17T00:52:30.163127",
        "used": false,
        "used_by": null
    },
    "OB1D1QG8DF1K": {
        "days": 1,
        "created_at": "2026-04-17T00:52:30.163150",
        "used": false,
        "used_by": null
    },
    "PK4JJNNQPKFL": {
        "days": 1,
        "created_at": "2026-04-17T00:52:30.163158",
        "used": false,
        "used_by": null
    },
    "CGWQMCOK6ODI": {
        "days": 1,
        "created_at": "2026-04-17T00:52:30.163166",
        "used": false,
        "used_by": null
    },
    "82VALW5D2IQH": {
        "days": 1,
        "created_at": "2026-04-17T00:52:30.163174",
        "used": false,
        "used_by": null
    },
    "U0DGZD3VVKAD": {
        "days": 1,
        "created_at": "2026-04-17T00:52:30.163182",
        "used": false,
        "used_by": null
    },
    "7NE0K2MEQUOR": {
        "days": 1,
        "created_at": "2026-04-17T00:52:30.163189",
        "used": false,
        "used_by": null
    },
    "V7JMYWXHPMDX": {
        "days": 1,
        "created_at": "2026-04-17T00:52:30.163196",
        "used": false,
        "used_by": null
    },
    "BUV1N6L6ERK0": {
        "days": 1,
        "created_at": "2026-04-17T00:52:30.163203",
        "used": false,
        "used_by": null
    },
    "A0JAJEM2JAJL": {
        "days": 1,
        "created_at": "2026-04-17T00:52:30.163210",
        "used": false,
        "used_by": null
    }
}